{
  "id": 2000011,
  "local": true,
  "slug": "hastelloy-pipe-flanges-corrosive-environments",
  "title": "Why Choose Hastelloy Pipe Flanges for Corrosive Environments",
  "description": "Discover why Hastelloy pipe flanges are the preferred choice for highly corrosive industrial applications. Learn about corrosion mechanisms and long-term benefits.",
  "date": "2026-01-22",
  "author": "Cheyanne Harris",
  "keywords": [
    "hastelloy pipe flange",
    "hastelloy flanges",
    "corrosive environments",
    "corrosion resistant flanges",
    "chemical processing"
  ],
  "featured": true,
  "image": "/images/blog/blog-1.png",
  "content": "<h1>Why Choose Hastelloy Pipe Flanges for Corrosive Environments</h1>\n<p>In industries dealing with aggressive chemicals, extreme temperatures, and corrosive media, equipment failure isn't just inconvenient—it's dangerous and expensive. <strong>Hastelloy pipe flanges</strong> have become the gold standard for critical applications where conventional materials simply can't survive. Here's why.</p>\n<h2>The True Cost of Corrosion</h2>\n<p>Before diving into why Hastelloy excels, let's understand what's at stake:</p>\n<h3>Financial Impact</h3>\n<ul>\n<li><strong>Unplanned downtime</strong>: $50,000 to $500,000+ per hour in large facilities</li>\n<li><strong>Replacement parts</strong>: Standard flanges may need replacement every 1-3 years</li>\n<li><strong>Labor costs</strong>: Emergency repairs cost 3-5x more than planned maintenance</li>\n<li><strong>Product loss</strong>: Contamination and waste from failed components</li>\n</ul>\n<h3>Safety Concerns</h3>\n<ul>\n<li>Chemical releases endangering personnel</li>\n<li>Fire and explosion risks from leaks</li>\n<li>Environmental contamination</li>\n<li>Regulatory penalties and shutdowns</li>\n</ul>\n<p>A single flange failure can cascade into millions in losses. <strong>Hastelloy pipe flanges</strong> eliminate these risks.</p>\n<h2>How Corrosion Attacks Standard Materials</h2>\n<h3>Uniform Corrosion</h3>\n<p>Standard carbon steel and even 316 stainless steel suffer from general surface attack in aggressive acids. While predictable, it leads to:</p>\n<ul>\n<li>Wall thinning</li>\n<li>Strength reduction</li>\n<li>Eventual failure</li>\n</ul>\n<p><strong>Hastelloy advantage</strong>: Extremely low general corrosion rates even in concentrated acids.</p>\n<h3>Pitting Corrosion</h3>\n<p>Chlorides create localized pits that penetrate deep into metal, often invisible until catastrophic failure occurs.</p>\n<p><strong>Hastelloy advantage</strong>: Molybdenum content provides exceptional pitting resistance. C276 and C22 grades demonstrate virtually no pitting in most chloride environments.</p>\n<h3>Crevice Corrosion</h3>\n<p>Occurs in confined spaces like gasket interfaces—exactly where <strong>flanges</strong> operate. Stagnant conditions concentrate corrosive species, accelerating attack.</p>\n<p><strong>Hastelloy advantage</strong>: High chromium and molybdenum content prevent crevice initiation and propagation.</p>\n<h3>Stress Corrosion Cracking (SCC)</h3>\n<p>Combination of tensile stress and corrosive environment causes sudden brittle fracture. Common in chloride-exposed stainless steels.</p>\n<p><strong>Hastelloy advantage</strong>: Nickel-base alloys are virtually immune to chloride-induced SCC.</p>\n<h3>Intergranular Corrosion</h3>\n<p>Grain boundaries become preferentially attacked, leading to catastrophic failure without obvious external signs.</p>\n<p><strong>Hastelloy advantage</strong>: Low carbon content and balanced chemistry prevent sensitization.</p>\n<h2>Performance in Specific Environments</h2>\n<h3>Hydrochloric Acid</h3>\n<p>One of the most aggressive common chemicals.</p>\n<p><strong>Standard stainless 316</strong>: Fails rapidly at any concentration\n<strong>Hastelloy B-3</strong>: Excellent up to boiling temperatures\n<strong>Hastelloy C276</strong>: Good across all concentrations</p>\n<h3>Sulfuric Acid</h3>\n<p>Widely used in chemical processes.</p>\n<p><strong>Standard stainless 316</strong>: Limited to dilute, cold conditions\n<strong>Hastelloy C276</strong>: Excellent in non-oxidizing conditions up to 120°C\n<strong>Hastelloy C22</strong>: Superior in oxidizing sulfuric acid</p>\n<h3>Acetic Acid</h3>\n<p>Common in chemical and pharmaceutical manufacturing.</p>\n<p><strong>Standard stainless 316</strong>: Adequate at low temperatures\n<strong>Hastelloy C276</strong>: Excellent up to 250°C, even with contaminants\n<strong>Service life</strong>: 20-30 years vs. 2-5 years for stainless</p>\n<h3>Chlorine &#x26; Hypochlorite</h3>\n<p>Extremely aggressive oxidizing chloride environments.</p>\n<p><strong>Standard stainless</strong>: Fails catastrophically\n<strong>Titanium</strong>: Good but expensive for flanges\n<strong>Hastelloy C22</strong>: Excellent, proven performance\n<strong>Hastelloy C276</strong>: Very good</p>\n<h3>Mixed Acids</h3>\n<p>Real-world processes often involve complex chemical mixtures.</p>\n<p><strong>Hastelloy advantage</strong>: Performs well across varying pH, oxidizing/reducing cycles, and temperature fluctuations where single-purpose alloys fail.</p>\n<h2>Temperature Performance</h2>\n<h3>High-Temperature Oxidation</h3>\n<p><strong>Hastelloy pipe flanges</strong> maintain protective oxide films at elevated temperatures:</p>\n<ul>\n<li><strong>316SS</strong>: Begins scaling above 600°C</li>\n<li><strong>Hastelloy C276</strong>: Stable to 650°C</li>\n<li><strong>Hastelloy X</strong>: Excellent to 1200°C</li>\n</ul>\n<h3>Thermal Cycling</h3>\n<p>Repeated heating/cooling stresses materials. Hastelloy's:</p>\n<ul>\n<li>High thermal fatigue resistance</li>\n<li>Stable mechanical properties</li>\n<li>Minimal phase changes</li>\n</ul>\n<p>Result in superior performance in cyclic applications like reactor systems and batch processes.</p>\n<h3>Low-Temperature Applications</h3>\n<p><strong>Hastelloy flanges</strong> retain:</p>\n<ul>\n<li>Impact toughness down to -196°C</li>\n<li>No ductile-to-brittle transition</li>\n<li>Ideal for cryogenic services</li>\n</ul>\n<h2>Real-World Case Studies</h2>\n<h3>Case Study 1: Chlor-Alkali Plant</h3>\n<p><strong>Problem</strong>: Stainless steel flanges failing every 18 months\n<strong>Solution</strong>: Upgraded to Hastelloy C22 flanges\n<strong>Result</strong>:</p>\n<ul>\n<li>12+ years service with no failures</li>\n<li>Eliminated annual shutdown for replacements</li>\n<li>ROI achieved in 3 years from reduced downtime</li>\n</ul>\n<h3>Case Study 2: Acetic Acid Production</h3>\n<p><strong>Problem</strong>: Frequent leaks at flange connections causing safety incidents\n<strong>Solution</strong>: Replaced critical flanges with Hastelloy C276\n<strong>Result</strong>:</p>\n<ul>\n<li>Zero leaks in 8 years of operation</li>\n<li>Improved safety ratings</li>\n<li>Reduced insurance premiums</li>\n</ul>\n<h3>Case Study 3: Pharmaceutical CIP System</h3>\n<p><strong>Problem</strong>: Contamination from corroded 316 flanges\n<strong>Solution</strong>: Complete system upgrade to Hastelloy C22\n<strong>Result</strong>:</p>\n<ul>\n<li>Eliminated contamination issues</li>\n<li>FDA inspection compliance</li>\n<li>Reduced cleaning validation requirements</li>\n</ul>\n<h2>Economic Justification</h2>\n<h3>Initial Cost Comparison</h3>\n<p>A 6\" 150# flange:</p>\n<ul>\n<li><strong>Carbon steel</strong>: $50</li>\n<li><strong>316 Stainless</strong>: $200</li>\n<li><strong>Hastelloy C276</strong>: $1,500</li>\n</ul>\n<p>Seems expensive? Consider:</p>\n<h3>Life-Cycle Cost Analysis (20-year period)</h3>\n<p><strong>Standard Stainless Steel Approach:</strong></p>\n<ul>\n<li>Initial cost: $200</li>\n<li>Replacements (6x): $1,200</li>\n<li>Installation labor (7x): $3,500</li>\n<li>Downtime costs (7x): $35,000</li>\n<li>Inspection costs: $2,000</li>\n<li><strong>Total: $41,900</strong></li>\n</ul>\n<p><strong>Hastelloy Approach:</strong></p>\n<ul>\n<li>Initial cost: $1,500</li>\n<li>Replacements: $0</li>\n<li>Installation labor (1x): $500</li>\n<li>Downtime costs: $0</li>\n<li>Inspection costs: $500</li>\n<li><strong>Total: $2,500</strong></li>\n</ul>\n<p><strong>Savings: $39,400 per flange over 20 years</strong></p>\n<h2>Selection Guidelines by Industry</h2>\n<h3>Chemical Processing</h3>\n<p><strong>Primary recommendation</strong>: Hastelloy C276</p>\n<ul>\n<li>Proven across widest range of chemicals</li>\n<li>Extensive performance database</li>\n<li>Best value for general service</li>\n</ul>\n<h3>Pulp &#x26; Paper</h3>\n<p><strong>Primary recommendation</strong>: Hastelloy C276</p>\n<ul>\n<li>Excellent in bleaching environments</li>\n<li>Resists chlorine dioxide</li>\n<li>Handles black liquor service</li>\n</ul>\n<h3>Pharmaceutical</h3>\n<p><strong>Primary recommendation</strong>: Hastelloy C22</p>\n<ul>\n<li>Superior in alternating CIP chemicals</li>\n<li>Excellent for high-purity applications</li>\n<li>Meets sanitary requirements</li>\n</ul>\n<h3>Oil &#x26; Gas</h3>\n<p><strong>Application specific</strong>:</p>\n<ul>\n<li>Sour gas: Hastelloy C276</li>\n<li>Severe sour: Hastelloy C22</li>\n<li>High H2S: Consider B-series</li>\n</ul>\n<h3>Pollution Control</h3>\n<p><strong>Primary recommendation</strong>: Hastelloy C276</p>\n<ul>\n<li>Industry standard for FGD systems</li>\n<li>Handles acidic condensates</li>\n<li>Proven in scrubber applications</li>\n</ul>\n<h2>Maintenance Advantages</h2>\n<h3>Inspection Intervals</h3>\n<p><strong>Standard materials</strong>: Every 6-12 months\n<strong>Hastelloy flanges</strong>: Every 2-5 years</p>\n<h3>Inspection Simplicity</h3>\n<ul>\n<li>Visual inspection often sufficient</li>\n<li>Reduced need for ultrasonic testing</li>\n<li>Longer intervals between shutdowns</li>\n</ul>\n<h3>Gasket Life</h3>\n<p>Stable flange surfaces mean:</p>\n<ul>\n<li>Longer gasket service life</li>\n<li>Fewer bolt retorques required</li>\n<li>Reduced fugitive emissions</li>\n</ul>\n<h2>Environmental and Safety Benefits</h2>\n<h3>Leak Prevention</h3>\n<p><strong>Hastelloy pipe flanges</strong> virtually eliminate:</p>\n<ul>\n<li>Fugitive emissions</li>\n<li>Groundwater contamination</li>\n<li>Air quality violations</li>\n<li>Worker exposure incidents</li>\n</ul>\n<h3>Sustainability</h3>\n<ul>\n<li>Reduced material consumption (longer life)</li>\n<li>Lower energy footprint (fewer replacements)</li>\n<li>Recyclable at end of life</li>\n<li>Minimal environmental impact during service</li>\n</ul>\n<h2>When Hastelloy May Be Overkill</h2>\n<p>Be smart about material selection:</p>\n<h3>Don't use Hastelloy when:</h3>\n<ul>\n<li>Water service (unless high chlorides)</li>\n<li>Mild chemical concentrations at ambient temperature</li>\n<li>Short-term or temporary installations</li>\n<li>Budget absolutely prohibits (but calculate lifecycle cost first)</li>\n</ul>\n<h3>Alternative materials to consider:</h3>\n<ul>\n<li><strong>316L SS</strong>: Mild conditions, lower temperatures</li>\n<li><strong>Alloy 20</strong>: Good compromise for moderately corrosive service</li>\n<li><strong>Titanium</strong>: Strong oxidizing acids (but check hydrogen concerns)</li>\n</ul>\n<h2>Specification Best Practices</h2>\n<p>When ordering <strong>Hastelloy flanges</strong>, specify:</p>\n<ol>\n<li><strong>Alloy grade</strong>: C276, C22, B-3, etc.</li>\n<li><strong>Size and pressure rating</strong>: Per ASME B16.5 or B16.47</li>\n<li><strong>Facing type</strong>: RF, FF, RTJ based on gasket</li>\n<li><strong>Special testing</strong>: PMI, hardness, dimensional</li>\n<li><strong>Documentation</strong>: Material certs, test reports, traceability</li>\n</ol>\n<h2>Conclusion</h2>\n<p><strong>Hastelloy pipe flanges</strong> aren't just components—they're insurance policies against catastrophic failure, environmental disasters, and economic losses. While the initial investment is higher, the total cost of ownership, improved safety, and operational reliability make them the obvious choice for corrosive service.</p>\n<p>The question isn't \"Can we afford Hastelloy flanges?\" but rather \"Can we afford not to use them?\"</p>\n<p>For critical applications in corrosive environments, Hastelloy provides peace of mind that no other material can match. Your operations, your workers, and your bottom line will thank you.</p>\n<p>Ready to upgrade your critical connections to Hastelloy? Our technical team can help you identify high-risk flanges in your system and provide detailed specifications for optimal performance.</p>\n",
  "readingTime": "7 min read",
  "isHtml": true
}